{
    "liked songs": [
        {
            "songTitle": "Law and Order: SVU theme song",
            "songGenre": "TV and Film Scores",
            "songIsLiked": true,
            "songArtist": "Mike Post"
        },
        {
            "songTitle": "Bluebird",
            "songGenre": "Country",
            "songIsLiked": true,
            "songArtist": "Miranda Lambert"
        },
        {
            "songTitle": "Who Knew",
            "songGenre": "Pop",
            "songIsLiked": true,
            "songArtist": "P!nk"
        }
    ],
    "name": "Liked Songs"
}